.gitignore
LICENSE.txt
MANIFEST.in
README.md
pytest.ini
setup.py
giwaxs_gui/__init__.py
giwaxs_gui/__main__.py
giwaxs_gui/__version.py
giwaxs_gui.egg-info/PKG-INFO
giwaxs_gui.egg-info/SOURCES.txt
giwaxs_gui.egg-info/dependency_links.txt
giwaxs_gui.egg-info/entry_points.txt
giwaxs_gui.egg-info/requires.txt
giwaxs_gui.egg-info/top_level.txt
giwaxs_gui/app/__init__.py
giwaxs_gui/app/actions_stack.py
giwaxs_gui/app/app.py
giwaxs_gui/app/debug_tracker.py
giwaxs_gui/app/geometry.py
giwaxs_gui/app/geometry_holder.py
giwaxs_gui/app/image_holder.py
giwaxs_gui/app/image_processing.py
giwaxs_gui/app/polar_image.py
giwaxs_gui/app/read_image.py
giwaxs_gui/app/transformations.py
giwaxs_gui/app/utils.py
giwaxs_gui/app/data_manager/__init__.py
giwaxs_gui/app/data_manager/data_manager.py
giwaxs_gui/app/data_manager/load_data.py
giwaxs_gui/app/data_manager/load_from_h5.py
giwaxs_gui/app/data_manager/save_data.py
giwaxs_gui/app/data_manager/save_h5.py
giwaxs_gui/app/data_manager/saving_parameters.py
giwaxs_gui/app/file_manager/__init__.py
giwaxs_gui/app/file_manager/config_manager.py
giwaxs_gui/app/file_manager/keys.py
giwaxs_gui/app/file_manager/npy_file_manager.py
giwaxs_gui/app/file_manager/object_file_manager.py
giwaxs_gui/app/file_manager/project_structure.py
giwaxs_gui/app/file_manager/read_fits.py
giwaxs_gui/app/file_manager/read_geometry.py
giwaxs_gui/app/file_manager/read_images.py
giwaxs_gui/app/file_manager/read_meta_roi.py
giwaxs_gui/app/file_manager/read_polar_images.py
giwaxs_gui/app/file_manager/read_radial_profile.py
giwaxs_gui/app/file_manager/read_roi_data.py
giwaxs_gui/app/fitting/__init__.py
giwaxs_gui/app/fitting/background.py
giwaxs_gui/app/fitting/fit.py
giwaxs_gui/app/fitting/fit_holder.py
giwaxs_gui/app/fitting/fit_object.py
giwaxs_gui/app/fitting/functions.py
giwaxs_gui/app/fitting/range_strategy.py
giwaxs_gui/app/fitting/utils.py
giwaxs_gui/app/profiles/__init__.py
giwaxs_gui/app/profiles/angular_profile.py
giwaxs_gui/app/profiles/basic_profile.py
giwaxs_gui/app/profiles/radial_profile.py
giwaxs_gui/app/rois/__init__.py
giwaxs_gui/app/rois/new_roi_dict.py
giwaxs_gui/app/rois/roi.py
giwaxs_gui/app/rois/roi_colors.py
giwaxs_gui/app/rois/roi_data.py
