Metadata-Version: 2.1
Name: giwaxs-gui
Version: 0.3.5.1
Summary: A GUI program for GIWAXS images analysis
Home-page: https://pypi.org/project/giwaxs-gui
Author: Vladimir Starostin
Author-email: vladimir.starostin@uni-tuebingen.de
License: GPLv3
Keywords: xray python giwaxs scientific-analysis
Platform: UNKNOWN
Requires-Python: >=3.7.2
License-File: LICENSE.txt
